wrapio/__init__.py
wrapio/helpers.py
wrapio/waits.py
wrapio-2.0.0.dist-info/LICENCE
wrapio-2.0.0.dist-info/METADATA
wrapio-2.0.0.dist-info/WHEEL
wrapio-2.0.0.dist-info/top_level.txt
wrapio-2.0.0.dist-info/RECORD
