Metadata-Version: 2.1
Name: wrapio
Version: 2.0.0
Summary: Handling event-based streams.
Home-page: https://github.com/Exahilosys/wrapio
Author: Exahilosys
License: MIT
Platform: UNKNOWN
Requires-Python: >=3.5
Provides-Extra: docs
